{
	"grades":{
		"Mean":"6.40909090909091",
		"Standard Deviation":"2.38510067589605"
	},
	"k201675":{
		"Mid_1st_Attempt":"5",
		"Mid_2nd_Attempt":"6",
		"26thMatchBonus":"1",
		"project":"16",
	},
	"k201740":{
		"Mid_1st_Attempt":"4",
		"Mid_2nd_Attempt":"6",
		"26thMatchBonus":"1",
		"project":"16",
	},
	"k201063":{
		"Mid_1st_Attempt":"4",
		"26thMatchBonus":"1",
		"23rdAprilBonus":"1",
		"7thMayBonus":"1",
		"project":"16",
	},
	"k200243":{
		"Mid_1st_Attempt":"2",
		"Mid_2nd_Attempt":"4",
		"26thMatchBonus":"1",
		"7thMayBonus":"1",
		"project":"16",
		"assignment1":"1",
		"assignment2":"0",
		"assignment3":"2",
		"assignment4":"2",
		"assignment5":"2",
	},
	"k200327":{
		"Mid_1st_Attempt":"6",
		"Mid_2nd_Attempt":"14.5",
		"26thMatchBonus":"1",
		"Extra Credit":"1",
		"7thMayBonus":"1",
		"project":"18",
		"assignment1":"1",
		"assignment2":"2",
		"assignment3":"2",
		"assignment4":"2",
		"assignment5":"2",
	},
	"k201754":{
		"Mid_1st_Attempt":"7",
		"Mid_2nd_Attempt":"9",
		"project":"19",
		"assignment1":"2",
		"assignment2":"2",
		"assignment3":"2",
		"assignment4":"2",
		"assignment5":"2",
	},
	"k201055":{
		"Mid_1st_Attempt":"7",
		"Mid_2nd_Attempt":"10",
		"project":"19",
	},
	"k200385":{
		"Mid_1st_Attempt":"6",
	},
	"k200481":{
		"Mid_1st_Attempt":"5",
		"Mid_2nd_Attempt":"8",
		"26thMatchBonus":"1",
		"23rdAprilBonus":"1",
		"7thMayBonus":"1",
		"project":"19",
		"assignment1":"2",
		"assignment2":"2",
		"assignment3":"2",
		"assignment4":"2",
		"assignment5":"2",
	},
	"k201643":{
		"Mid_1st_Attempt":"4",
		"Mid_2nd_Attempt":"6",
		"26thMatchBonus":"1",
		"project":"16",
		"assignment1":"1",
		"assignment2":"2",
		"assignment3":"2",
		"assignment4":"2",
		"assignment5":"2",
	},
	"k200375":{
		"Mid_1st_Attempt":"4",
		"Mid_2nd_Attempt":"5",
		"26thMatchBonus":"1",
		"7thMayBonus":"1",
		"project":"19",
		"assignment1":"1",
		"assignment2":"2",
		"assignment3":"2",
		"assignment4":"2",
		"assignment5":"2",
	},
	"k200174":{
		"Mid_1st_Attempt":"6",
		"26thMatchBonus":"1",
		"project":"18",
	},
	"k201752":{
		"Mid_1st_Attempt":"6",
		"26thMatchBonus":"1",
		"project":"18"
	},
	"k200137":{
		"Mid_1st_Attempt":"6",
		"26thMatchBonus":"1",
		"project":"18",
	},
	"k200324":{
		"Mid_1st_Attempt":"6",
		"26thMatchBonus":"1",
		"7thMayBonus":"1",
		"project":"19",
		"assignment1":"2",
		"assignment2":"2",
		"assignment3":"2",
		"assignment4":"2",
		"assignment5":"2",
	},
	"k200462":{
		"Mid_1st_Attempt":"6",
		"7thMayBonus":"1",
		"project":"18",
		"assignment1":"1",
		"assignment2":"2",
		"assignment3":"2",
		"assignment4":"2",
		"assignment5":"2",
	},
	"k201640":{
		"Mid_1st_Attempt":"6",
		"project":"16"
	},
	"k200191":{
		"todo":"",
		"Mid_1st_Attempt":"0",
		"Mid_2nd_Attempt":"0",
		"26thMatchBonus":"1",
		"7thMayBonus":"1",
		"project":"16",
	},
	"k201691":{
		"Mid_1st_Attempt":"6",
		"project":"16",
	},
	"k200498":{
		"Mid_1st_Attempt":"6",
		"26thMatchBonus":"1",
		"project":"18",
		"assignment1":"1",
		"assignment2":"2",
		"assignment3":"2",
		"assignment4":"2",
		"assignment5":"2",
	},
	"k201050":{
		"Mid_1st_Attempt":"5",
		"26thMatchBonus":"1",
		"assignment1":"2",
		"assignment2":"0",
		"assignment3":"2",
		"assignment4":"2",
		"assignment5":"2",
	},
	"k201693":{
		"Mid_1st_Attempt":"5",
		"project":"16",
	},
	"k201646":{
		"Mid_1st_Attempt":"5",
		"26thMatchBonus":"1",
		"project":"16",
		"assignment1":"1",
		"assignment2":"2",
		"assignment3":"2",
		"assignment4":"2",
		"assignment5":"2",
	},
	"k201751":{
		"Mid_1st_Attempt":"5",
		"project":"16",
	},
	"k200496":{
		"Mid_1st_Attempt":"5",
		"26thMatchBonus":"1",
		"7thMayBonus":"1"
	},
	"k201051":{
		"Mid_1st_Attempt":"4",
		"26thMatchBonus":"1",
		"7thMayBonus":"1",
		"project":"20",
		"assignment1":"2",
		"assignment2":"2",
		"assignment3":"2",
		"assignment4":"2",
		"assignment5":"2",
	},
	"k201671":{
		"Mid_1st_Attempt":"4",
		"26thMatchBonus":"1",
		"7thMayBonus":"1",
		"project":"19",
		"assignment1":"1",
		"assignment2":"1",
		"assignment3":"2",
		"assignment4":"2",
		"assignment5":"2",
	},
	"k200301":{
		"Mid_1st_Attempt":"4",
		"26thMatchBonus":"1",
		"project":"19",
		"assignment1":"0",
		"assignment2":"1",
		"assignment3":"2",
		"assignment4":"2",
		"assignment5":"2",
	},
	"k200127":{
		"Mid_1st_Attempt":"4",
		"project":"16",
	},
	"k200480":{
		"Mid_1st_Attempt":"3",
		"project":"16",
		"assignment1":"2",
		"assignment2":"2",
		"assignment3":"2",
		"assignment4":"2",
		"assignment5":"2",
	},
	"k200341":{
		"Mid_1st_Attempt":"3",
		"26thMatchBonus":"1",
		"project":"19",
		"assignment1":"1",
		"assignment2":"2",
		"assignment3":"2",
		"assignment4":"2",
		"assignment5":"2",
	},
	"k200336":{
		"Mid_1st_Attempt":"3",
		"project":"18",
	},
	"k200358":{
		"Mid_1st_Attempt":"4",
		"26thMatchBonus":"1",
		"23rdAprilBonus":"1",
		"7thMayBonus":"1",
		"Honesty":"1",
		"project":"17",
	},
	"k200357":{
		"todo":"",
		"Mid_1st_Attempt":"0",
		"Mid_2nd_Attempt":"0",
		"26thMatchBonus":"0",
		"7thMayBonus":"1",
		"project":"19",
		"assignment1":"1",
		"assignment2":"2",
		"assignment3":"2",
		"assignment4":"2",
		"assignment5":"2",
	},
	"k200329":{
		"Mid_1st_Attempt":"0",
		"Mid_2nd_Attempt":"0",
		"26thMatchBonus":"1"
	}
}
